kde/__init__.py
kde/kde.py
kde-0.0.3.dist-info/LICENSE
kde-0.0.3.dist-info/METADATA
kde-0.0.3.dist-info/WHEEL
kde-0.0.3.dist-info/top_level.txt
kde-0.0.3.dist-info/RECORD
